fakesmtpd/__init__.py
fakesmtpd/args.py
fakesmtpd/commands.py
fakesmtpd/connection.py
fakesmtpd/mbox.py
fakesmtpd/server.py
fakesmtpd/smtp.py
fakesmtpd/state.py
fakesmtpd/syntax.py
fakesmtpd-2025.10.0.dist-info/METADATA
fakesmtpd-2025.10.0.dist-info/WHEEL
fakesmtpd-2025.10.0.dist-info/entry_points.txt
fakesmtpd-2025.10.0.dist-info/licenses/LICENSE
fakesmtpd-2025.10.0.dist-info/RECORD
