Metadata-Version: 2.4
Name: FakeSMTPd
Version: 2025.10.0
Summary: SMTP server for testing mail functionality
License-Expression: MIT
License-File: LICENSE
Keywords: SMTP,mail,testing
Author: Sebastian Rittau
Author-email: srittau@rittau.biz
Requires-Python: >= 3.10
Classifier: Development Status :: 5 - Production/Stable
Classifier: Topic :: Communications :: Email :: Mail Transport Agents
Classifier: Topic :: Software Development :: Testing
Requires-Dist: typing-extensions (>=4.0.1,<5)
Project-URL: Changes, https://github.com/srittau/fakesmtpd/blob/main/CHANGELOG.md
Project-URL: GitHub, https://github.com/srittau/fakesmtpd
Project-URL: Homepage, https://github.com/srittau/fakesmtpd
Project-URL: Issues, https://github.com/srittau/fakesmtpd/issues
